Workbook

Sheet Start here
B2: Pen Show Tracker
B3: Inventory, pricing, sales and P&L for the 2026 US pen show circuit.
B6: How to use it
B7: 1. Shows tab — fill in your table fee, travel, lodging and meals for each show, and VERIFY the sales tax rate.
B8: 2. Inventory tab — one row per SKU. Type cost, show price and floor price. Everything grey-black is calculated.
B9: 3. Sales Log tab — one row per item sold. Pick the SKU from the dropdown; name, cost and tax fill in for you.
B10: 4. Dashboard tab — per-show P&L and your end-of-day payment reconciliation. Nothing to type here.
B12: Colour code
B13: Blue text you type it
B14: Black text calculated — overwriting it breaks the sheet
B15: Green text pulled from another tab
B16: Yellow fill a key assumption to confirm before the show
... B36: • Back this file up every night. One file on one laptop is not a backup.

Sheet Dashboard
A1: Dashboard — did the show actually make money?
A2: Everything here is calculated from the Shows and Sales Log tabs. Sales tax collected is a liability you remit to the state; it is never revenue and never profit.
A3: Show | B3: Sales lines | C3: Units | D3: Revenue | E3: COGS | F3: Gross profit | G3: Margin % | H3: Card fees | I3: Show costs | J3: NET PROFIT | K3: Break-even revenue | L3: Sales tax collected | M3: Cash | N3: Zelle | O3: Venmo | P3: Card | Q3: Check | R3: Trade
A4: =IF(Shows!$A$4="","",Shows!$A$4) | B4: =IF($A4="","",COUNTIFS('Sales Log'!$B$4:$B$503,$A4)) | C4: =IF($A4="","",SUMIFS('Sales Log'!$E$4:$E$503,'Sales Log'!$B$4:$B$503,$A4)) | D4: =IF($A4="","",SUMIFS('Sales Log'!$J$4:$J$503,'Sales Log'!$B$4:$B$503,$A4)) | E4: =IF($A4="","",SUMIFS('Sales Log'!$L$4:$L$503,'Sales Log'!$B$4:$B$503,$A4)) | F4: =IF($A4="","",D4-E4) | G4: =IF(N(D4)>0,F4/D4,"") | H4: =IF($A4="","",SUMIFS('Sales Log'!$P$4:$P$503,'Sales Log'!$B$4:$B$503,$A4)) | I4: =IF($A4="","",IFERROR(INDEX(Shows!$O$4:$O$23,MATCH($A4,Shows!$A$4:$A$23,0)),0)) | J4: =IF($A4="","",F4-H4-I4) | K4: =IF(N(G4)>0,(I4+H4)/G4,"") | L4: =IF($A4="","",SUMIFS('Sales Log'!$K$4:$K$503,'Sales Log'!$B$4:$B$503,$A4)) | M4: =IF($A4="","",SUMIFS('Sales Log'!$Q$4:$Q$503,'Sales Log'!$B$4:$B$503,$A4,'Sales Log'!$N$4:$N$503,"Cash")) | N4: =IF($A4="","",SUMIFS('Sales Log'!$Q$4:$Q$503,'Sales Log'!$B$4:$B$503,$A4,'Sales Log'!$N$4:$N$503,"Zelle")) | O4: =IF($A4="","",SUMIFS('Sales Log'!$Q$4:$Q$503,'Sales Log'!$B$4:$B$503,$A4,'Sales Log'!$N$4:$N$503,"Venmo")) | P4: =IF($A4="","",SUMIFS('Sales Log'!$Q$4:$Q$503,'Sales Log'!$B$4:$B$503,$A4,'Sales Log'!$N$4:$N$503,"Card")) | Q4: =IF($A4="","",SUMIFS('Sales Log'!$Q$4:$Q$503,'Sales Log'!$B$4:$B$503,$A4,'Sales Log'!$N$4:$N$503,"Check")) | R4: =IF($A4="","",SUMIFS('Sales Log'!$Q$4:$Q$503,'Sales Log'!$B$4:$B$503,$A4,'Sales Log'!$N$4:$N$503,"Trade"))
A5: =IF(Shows!$A$5="","",Shows!$A$5) | B5: =IF($A5="","",COUNTIFS('Sales Log'!$B$4:$B$503,$A5)) | C5: =IF($A5="","",SUMIFS('Sales Log'!$E$4:$E$503,'Sales Log'!$B$4:$B$503,$A5)) | D5: =IF($A5="","",SUMIFS('Sales Log'!$J$4:$J$503,'Sales Log'!$B$4:$B$503,$A5)) | E5: =IF($A5="","",SUMIFS('Sales Log'!$L$4:$L$503,'Sales Log'!$B$4:$B$503,$A5)) | F5: =IF($A5="","",D5-E5) | G5: =IF(N(D5)>0,F5/D5,"") | H5: =IF($A5="","",SUMIFS('Sales Log'!$P$4:$P$503,'Sales Log'!$B$4:$B$503,$A5)) | I5: =IF($A5="","",IFERROR(INDEX(Shows!$O$4:$O$23,MATCH($A5,Shows!$A$4:$A$23,0)),0)) | J5: =IF($A5="","",F5-H5-I5) | K5: =IF(N(G5)>0,(I5+H5)/G5,"") | L5: =IF($A5="","",SUMIFS('Sales Log'!$K$4:$K$503,'Sales Log'!$B$4:$B$503,$A5)) | M5: =IF($A5="","",SUMIFS('Sales Log'!$Q$4:$Q$503,'Sales Log'!$B$4:$B$503,$A5,'Sales Log'!$N$4:$N$503,"Cash")) | N5: =IF($A5="","",SUMIFS('Sales Log'!$Q$4:$Q$503,'Sales Log'!$B$4:$B$503,$A5,'Sales Log'!$N$4:$N$503,"Zelle")) | O5: =IF($A5="","",SUMIFS('Sales Log'!$Q$4:$Q$503,'Sales Log'!$B$4:$B$503,$A5,'Sales Log'!$N$4:$N$503,"Venmo")) | P5: =IF($A5="","",SUMIFS('Sales Log'!$Q$4:$Q$503,'Sales Log'!$B$4:$B$503,$A5,'Sales Log'!$N$4:$N$503,"Card")) | Q5: =IF($A5="","",SUMIFS('Sales Log'!$Q$4:$Q$503,'Sales Log'!$B$4:$B$503,$A5,'Sales Log'!$N$4:$N$503,"Check")) | R5: =IF($A5="","",SUMIFS('Sales Log'!$Q$4:$Q$503,'Sales Log'!$B$4:$B$503,$A5,'Sales Log'!$N$4:$N$503,"Trade"))
A6: =IF(Shows!$A$6="","",Shows!$A$6) | B6: =IF($A6="","",COUNTIFS('Sales Log'!$B$4:$B$503,$A6)) | C6: =IF($A6="","",SUMIFS('Sales Log'!$E$4:$E$503,'Sales Log'!$B$4:$B$503,$A6)) | D6: =IF($A6="","",SUMIFS('Sales Log'!$J$4:$J$503,'Sales Log'!$B$4:$B$503,$A6)) | E6: =IF($A6="","",SUMIFS('Sales Log'!$L$4:$L$503,'Sales Log'!$B$4:$B$503,$A6)) | F6: =IF($A6="","",D6-E6) | G6: =IF(N(D6)>0,F6/D6,"") | H6: =IF($A6="","",SUMIFS('Sales Log'!$P$4:$P$503,'Sales Log'!$B$4:$B$503,$A6)) | I6: =IF($A6="","",IFERROR(INDEX(Shows!$O$4:$O$23,MATCH($A6,Shows!$A$4:$A$23,0)),0)) | J6: =IF($A6="","",F6-H6-I6) | K6: =IF(N(G6)>0,(I6+H6)/G6,"") | L6: =IF($A6="","",SUMIFS('Sales Log'!$K$4:$K$503,'Sales Log'!$B$4:$B$503,$A6)) | M6: =IF($A6="","",SUMIFS('Sales Log'!$Q$4:$Q$503,'Sales Log'!$B$4:$B$503,$A6,'Sales Log'!$N$4:$N$503,"Cash")) | N6: =IF($A6="","",SUMIFS('Sales Log'!$Q$4:$Q$503,'Sales Log'!$B$4:$B$503,$A6,'Sales Log'!$N$4:$N$503,"Zelle")) | O6: =IF($A6="","",SUMIFS('Sales Log'!$Q$4:$Q$503,'Sales Log'!$B$4:$B$503,$A6,'Sales Log'!$N$4:$N$503,"Venmo")) | P6: =IF($A6="","",SUMIFS('Sales Log'!$Q$4:$Q$503,'Sales Log'!$B$4:$B$503,$A6,'Sales Log'!$N$4:$N$503,"Card")) | Q6: =IF($A6="","",SUMIFS('Sales Log'!$Q$4:$Q$503,'Sales Log'!$B$4:$B$503,$A6,'Sales Log'!$N$4:$N$503,"Check")) | R6: =IF($A6="","",SUMIFS('Sales Log'!$Q$4:$Q$503,'Sales Log'!$B$4:$B$503,$A6,'Sales Log'!$N$4:$N$503,"Trade"))
A7: =IF(Shows!$A$7="","",Shows!$A$7) | B7: =IF($A7="","",COUNTIFS('Sales Log'!$B$4:$B$503,$A7)) | C7: =IF($A7="","",SUMIFS('Sales Log'!$E$4:$E$503,'Sales Log'!$B$4:$B$503,$A7)) | D7: =IF($A7="","",SUMIFS('Sales Log'!$J$4:$J$503,'Sales Log'!$B$4:$B$503,$A7)) | E7: =IF($A7="","",SUMIFS('Sales Log'!$L$4:$L$503,'Sales Log'!$B$4:$B$503,$A7)) | F7: =IF($A7="","",D7-E7) | G7: =IF(N(D7)>0,F7/D7,"") | H7: =IF($A7="","",SUMIFS('Sales Log'!$P$4:$P$503,'Sales Log'!$B$4:$B$503,$A7)) | I7: =IF($A7="","",IFERROR(INDEX(Shows!$O$4:$O$23,MATCH($A7,Shows!$A$4:$A$23,0)),0)) | J7: =IF($A7="","",F7-H7-I7) | K7: =IF(N(G7)>0,(I7+H7)/G7,"") | L7: =IF($A7="","",SUMIFS('Sales Log'!$K$4:$K$503,'Sales Log'!$B$4:$B$503,$A7)) | M7: =IF($A7="","",SUMIFS('Sales Log'!$Q$4:$Q$503,'Sales Log'!$B$4:$B$503,$A7,'Sales Log'!$N$4:$N$503,"Cash")) | N7: =IF($A7="","",SUMIFS('Sales Log'!$Q$4:$Q$503,'Sales Log'!$B$4:$B$503,$A7,'Sales Log'!$N$4:$N$503,"Zelle")) | O7: =IF($A7="","",SUMIFS('Sales Log'!$Q$4:$Q$503,'Sales Log'!$B$4:$B$503,$A7,'Sales Log'!$N$4:$N$503,"Venmo")) | P7: =IF($A7="","",SUMIFS('Sales Log'!$Q$4:$Q$503,'Sales Log'!$B$4:$B$503,$A7,'Sales Log'!$N$4:$N$503,"Card")) | Q7: =IF($A7="","",SUMIFS('Sales Log'!$Q$4:$Q$503,'Sales Log'!$B$4:$B$503,$A7,'Sales Log'!$N$4:$N$503,"Check")) | R7: =IF($A7="","",SUMIFS('Sales Log'!$Q$4:$Q$503,'Sales Log'!$B$4:$B$503,$A7,'Sales Log'!$N$4:$N$503,"Trade"))
A8: =IF(Shows!$A$8="","",Shows!$A$8) | B8: =IF($A8="","",COUNTIFS('Sales Log'!$B$4:$B$503,$A8)) | C8: =IF($A8="","",SUMIFS('Sales Log'!$E$4:$E$503,'Sales Log'!$B$4:$B$503,$A8)) | D8: =IF($A8="","",SUMIFS('Sales Log'!$J$4:$J$503,'Sales Log'!$B$4:$B$503,$A8)) | E8: =IF($A8="","",SUMIFS('Sales Log'!$L$4:$L$503,'Sales Log'!$B$4:$B$503,$A8)) | F8: =IF($A8="","",D8-E8) | G8: =IF(N(D8)>0,F8/D8,"") | H8: =IF($A8="","",SUMIFS('Sales Log'!$P$4:$P$503,'Sales Log'!$B$4:$B$503,$A8)) | I8: =IF($A8="","",IFERROR(INDEX(Shows!$O$4:$O$23,MATCH($A8,Shows!$A$4:$A$23,0)),0)) | J8: =IF($A8="","",F8-H8-I8) | K8: =IF(N(G8)>0,(I8+H8)/G8,"") | L8: =IF($A8="","",SUMIFS('Sales Log'!$K$4:$K$503,'Sales Log'!$B$4:$B$503,$A8)) | M8: =IF($A8="","",SUMIFS('Sales Log'!$Q$4:$Q$503,'Sales Log'!$B$4:$B$503,$A8,'Sales Log'!$N$4:$N$503,"Cash")) | N8: =IF($A8="","",SUMIFS('Sales Log'!$Q$4:$Q$503,'Sales Log'!$B$4:$B$503,$A8,'Sales Log'!$N$4:$N$503,"Zelle")) | O8: =IF($A8="","",SUMIFS('Sales Log'!$Q$4:$Q$503,'Sales Log'!$B$4:$B$503,$A8,'Sales Log'!$N$4:$N$503,"Venmo")) | P8: =IF($A8="","",SUMIFS('Sales Log'!$Q$4:$Q$503,'Sales Log'!$B$4:$B$503,$A8,'Sales Log'!$N$4:$N$503,"Card")) | Q8: =IF($A8="","",SUMIFS('Sales Log'!$Q$4:$Q$503,'Sales Log'!$B$4:$B$503,$A8,'Sales Log'!$N$4:$N$503,"Check")) | R8: =IF($A8="","",SUMIFS('Sales Log'!$Q$4:$Q$503,'Sales Log'!$B$4:$B$503,$A8,'Sales Log'!$N$4:$N$503,"Trade"))
A9: =IF(Shows!$A$9="","",Shows!$A$9) | B9: =IF($A9="","",COUNTIFS('Sales Log'!$B$4:$B$503,$A9)) | C9: =IF($A9="","",SUMIFS('Sales Log'!$E$4:$E$503,'Sales Log'!$B$4:$B$503,$A9)) | D9: =IF($A9="","",SUMIFS('Sales Log'!$J$4:$J$503,'Sales Log'!$B$4:$B$503,$A9)) | E9: =IF($A9="","",SUMIFS('Sales Log'!$L$4:$L$503,'Sales Log'!$B$4:$B$503,$A9)) | F9: =IF($A9="","",D9-E9) | G9: =IF(N(D9)>0,F9/D9,"") | H9: =IF($A9="","",SUMIFS('Sales Log'!$P$4:$P$503,'Sales Log'!$B$4:$B$503,$A9)) | I9: =IF($A9="","",IFERROR(INDEX(Shows!$O$4:$O$23,MATCH($A9,Shows!$A$4:$A$23,0)),0)) | J9: =IF($A9="","",F9-H9-I9) | K9: =IF(N(G9)>0,(I9+H9)/G9,"") | L9: =IF($A9="","",SUMIFS('Sales Log'!$K$4:$K$503,'Sales Log'!$B$4:$B$503,$A9)) | M9: =IF($A9="","",SUMIFS('Sales Log'!$Q$4:$Q$503,'Sales Log'!$B$4:$B$503,$A9,'Sales Log'!$N$4:$N$503,"Cash")) | N9: =IF($A9="","",SUMIFS('Sales Log'!$Q$4:$Q$503,'Sales Log'!$B$4:$B$503,$A9,'Sales Log'!$N$4:$N$503,"Zelle")) | O9: =IF($A9="","",SUMIFS('Sales Log'!$Q$4:$Q$503,'Sales Log'!$B$4:$B$503,$A9,'Sales Log'!$N$4:$N$503,"Venmo")) | P9: =IF($A9="","",SUMIFS('Sales Log'!$Q$4:$Q$503,'Sales Log'!$B$4:$B$503,$A9,'Sales Log'!$N$4:$N$503,"Card")) | Q9: =IF($A9="","",SUMIFS('Sales Log'!$Q$4:$Q$503,'Sales Log'!$B$4:$B$503,$A9,'Sales Log'!$N$4:$N$503,"Check")) | R9: =IF($A9="","",SUMIFS('Sales Log'!$Q$4:$Q$503,'Sales Log'!$B$4:$B$503,$A9,'Sales Log'!$N$4:$N$503,"Trade"))
A10: =IF(Shows!$A$10="","",Shows!$A$10) | B10: =IF($A10="","",COUNTIFS('Sales Log'!$B$4:$B$503,$A10)) | C10: =IF($A10="","",SUMIFS('Sales Log'!$E$4:$E$503,'Sales Log'!$B$4:$B$503,$A10)) | D10: =IF($A10="","",SUMIFS('Sales Log'!$J$4:$J$503,'Sales Log'!$B$4:$B$503,$A10)) | E10: =IF($A10="","",SUMIFS('Sales Log'!$L$4:$L$503,'Sales Log'!$B$4:$B$503,$A10)) | F10: =IF($A10="","",D10-E10) | G10: =IF(N(D10)>0,F10/D10,"") | H10: =IF($A10="","",SUMIFS('Sales Log'!$P$4:$P$503,'Sales Log'!$B$4:$B$503,$A10)) | I10: =IF($A10="","",IFERROR(INDEX(Shows!$O$4:$O$23,MATCH($A10,Shows!$A$4:$A$23,0)),0)) | J10: =IF($A10="","",F10-H10-I10) | K10: =IF(N(G10)>0,(I10+H10)/G10,"") | L10: =IF($A10="","",SUMIFS('Sales Log'!$K$4:$K$503,'Sales Log'!$B$4:$B$503,$A10)) | M10: =IF($A10="","",SUMIFS('Sales Log'!$Q$4:$Q$503,'Sales Log'!$B$4:$B$503,$A10,'Sales Log'!$N$4:$N$503,"Cash")) | N10: =IF($A10="","",SUMIFS('Sales Log'!$Q$4:$Q$503,'Sales Log'!$B$4:$B$503,$A10,'Sales Log'!$N$4:$N$503,"Zelle")) | O10: =IF($A10="","",SUMIFS('Sales Log'!$Q$4:$Q$503,'Sales Log'!$B$4:$B$503,$A10,'Sales Log'!$N$4:$N$503,"Venmo")) | P10: =IF($A10="","",SUMIFS('Sales Log'!$Q$4:$Q$503,'Sales Log'!$B$4:$B$503,$A10,'Sales Log'!$N$4:$N$503,"Card")) | Q10: =IF($A10="","",SUMIFS('Sales Log'!$Q$4:$Q$503,'Sales Log'!$B$4:$B$503,$A10,'Sales Log'!$N$4:$N$503,"Check")) | R10: =IF($A10="","",SUMIFS('Sales Log'!$Q$4:$Q$503,'Sales Log'!$B$4:$B$503,$A10,'Sales Log'!$N$4:$N$503,"Trade"))
A11: =IF(Shows!$A$11="","",Shows!$A$11) | B11: =IF($A11="","",COUNTIFS('Sales Log'!$B$4:$B$503,$A11)) | C11: =IF($A11="","",SUMIFS('Sales Log'!$E$4:$E$503,'Sales Log'!$B$4:$B$503,$A11)) | D11: =IF($A11="","",SUMIFS('Sales Log'!$J$4:$J$503,'Sales Log'!$B$4:$B$503,$A11)) | E11: =IF($A11="","",SUMIFS('Sales Log'!$L$4:$L$503,'Sales Log'!$B$4:$B$503,$A11)) | F11: =IF($A11="","",D11-E11) | G11: =IF(N(D11)>0,F11/D11,"") | H11: =IF($A11="","",SUMIFS('Sales Log'!$P$4:$P$503,'Sales Log'!$B$4:$B$503,$A11)) | I11: =IF($A11="","",IFERROR(INDEX(Shows!$O$4:$O$23,MATCH($A11,Shows!$A$4:$A$23,0)),0)) | J11: =IF($A11="","",F11-H11-I11) | K11: =IF(N(G11)>0,(I11+H11)/G11,"") | L11: =IF($A11="","",SUMIFS('Sales Log'!$K$4:$K$503,'Sales Log'!$B$4:$B$503,$A11)) | M11: =IF($A11="","",SUMIFS('Sales Log'!$Q$4:$Q$503,'Sales Log'!$B$4:$B$503,$A11,'Sales Log'!$N$4:$N$503,"Cash")) | N11: =IF($A11="","",SUMIFS('Sales Log'!$Q$4:$Q$503,'Sales Log'!$B$4:$B$503,$A11,'Sales Log'!$N$4:$N$503,"Zelle")) | O11: =IF($A11="","",SUMIFS('Sales Log'!$Q$4:$Q$503,'Sales Log'!$B$4:$B$503,$A11,'Sales Log'!$N$4:$N$503,"Venmo")) | P11: =IF($A11="","",SUMIFS('Sales Log'!$Q$4:$Q$503,'Sales Log'!$B$4:$B$503,$A11,'Sales Log'!$N$4:$N$503,"Card")) | Q11: =IF($A11="","",SUMIFS('Sales Log'!$Q$4:$Q$503,'Sales Log'!$B$4:$B$503,$A11,'Sales Log'!$N$4:$N$503,"Check")) | R11: =IF($A11="","",SUMIFS('Sales Log'!$Q$4:$Q$503,'Sales Log'!$B$4:$B$503,$A11,'Sales Log'!$N$4:$N$503,"Trade"))
A12: =IF(Shows!$A$12="","",Shows!$A$12) | B12: =IF($A12="","",COUNTIFS('Sales Log'!$B$4:$B$503,$A12)) | C12: =IF($A12="","",SUMIFS('Sales Log'!$E$4:$E$503,'Sales Log'!$B$4:$B$503,$A12)) | D12: =IF($A12="","",SUMIFS('Sales Log'!$J$4:$J$503,'Sales Log'!$B$4:$B$503,$A12)) | E12: =IF($A12="","",SUMIFS('Sales Log'!$L$4:$L$503,'Sales Log'!$B$4:$B$503,$A12)) | F12: =IF($A12="","",D12-E12) | G12: =IF(N(D12)>0,F12/D12,"") | H12: =IF($A12="","",SUMIFS('Sales Log'!$P$4:$P$503,'Sales Log'!$B$4:$B$503,$A12)) | I12: =IF($A12="","",IFERROR(INDEX(Shows!$O$4:$O$23,MATCH($A12,Shows!$A$4:$A$23,0)),0)) | J12: =IF($A12="","",F12-H12-I12) | K12: =IF(N(G12)>0,(I12+H12)/G12,"") | L12: =IF($A12="","",SUMIFS('Sales Log'!$K$4:$K$503,'Sales Log'!$B$4:$B$503,$A12)) | M12: =IF($A12="","",SUMIFS('Sales Log'!$Q$4:$Q$503,'Sales Log'!$B$4:$B$503,$A12,'Sales Log'!$N$4:$N$503,"Cash")) | N12: =IF($A12="","",SUMIFS('Sales Log'!$Q$4:$Q$503,'Sales Log'!$B$4:$B$503,$A12,'Sales Log'!$N$4:$N$503,"Zelle")) | O12: =IF($A12="","",SUMIFS('Sales Log'!$Q$4:$Q$503,'Sales Log'!$B$4:$B$503,$A12,'Sales Log'!$N$4:$N$503,"Venmo")) | P12: =IF($A12="","",SUMIFS('Sales Log'!$Q$4:$Q$503,'Sales Log'!$B$4:$B$503,$A12,'Sales Log'!$N$4:$N$503,"Card")) | Q12: =IF($A12="","",SUMIFS('Sales Log'!$Q$4:$Q$503,'Sales Log'!$B$4:$B$503,$A12,'Sales Log'!$N$4:$N$503,"Check")) | R12: =IF($A12="","",SUMIFS('Sales Log'!$Q$4:$Q$503,'Sales Log'!$B$4:$B$503,$A12,'Sales Log'!$N$4:$N$503,"Trade"))
A13: =IF(Shows!$A$13="","",Shows!$A$13) | B13: =IF($A13="","",COUNTIFS('Sales Log'!$B$4:$B$503,$A13)) | C13: =IF($A13="","",SUMIFS('Sales Log'!$E$4:$E$503,'Sales Log'!$B$4:$B$503,$A13)) | D13: =IF($A13="","",SUMIFS('Sales Log'!$J$4:$J$503,'Sales Log'!$B$4:$B$503,$A13)) | E13: =IF($A13="","",SUMIFS('Sales Log'!$L$4:$L$503,'Sales Log'!$B$4:$B$503,$A13)) | F13: =IF($A13="","",D13-E13) | G13: =IF(N(D13)>0,F13/D13,"") | H13: =IF($A13="","",SUMIFS('Sales Log'!$P$4:$P$503,'Sales Log'!$B$4:$B$503,$A13)) | I13: =IF($A13="","",IFERROR(INDEX(Shows!$O$4:$O$23,MATCH($A13,Shows!$A$4:$A$23,0)),0)) | J13: =IF($A13="","",F13-H13-I13) | K13: =IF(N(G13)>0,(I13+H13)/G13,"") | L13: =IF($A13="","",SUMIFS('Sales Log'!$K$4:$K$503,'Sales Log'!$B$4:$B$503,$A13)) | M13: =IF($A13="","",SUMIFS('Sales Log'!$Q$4:$Q$503,'Sales Log'!$B$4:$B$503,$A13,'Sales Log'!$N$4:$N$503,"Cash")) | N13: =IF($A13="","",SUMIFS('Sales Log'!$Q$4:$Q$503,'Sales Log'!$B$4:$B$503,$A13,'Sales Log'!$N$4:$N$503,"Zelle")) | O13: =IF($A13="","",SUMIFS('Sales Log'!$Q$4:$Q$503,'Sales Log'!$B$4:$B$503,$A13,'Sales Log'!$N$4:$N$503,"Venmo")) | P13: =IF($A13="","",SUMIFS('Sales Log'!$Q$4:$Q$503,'Sales Log'!$B$4:$B$503,$A13,'Sales Log'!$N$4:$N$503,"Card")) | Q13: =IF($A13="","",SUMIFS('Sales Log'!$Q$4:$Q$503,'Sales Log'!$B$4:$B$503,$A13,'Sales Log'!$N$4:$N$503,"Check")) | R13: =IF($A13="","",SUMIFS('Sales Log'!$Q$4:$Q$503,'Sales Log'!$B$4:$B$503,$A13,'Sales Log'!$N$4:$N$503,"Trade"))
A14: =IF(Shows!$A$14="","",Shows!$A$14) | B14: =IF($A14="","",COUNTIFS('Sales Log'!$B$4:$B$503,$A14)) | C14: =IF($A14="","",SUMIFS('Sales Log'!$E$4:$E$503,'Sales Log'!$B$4:$B$503,$A14)) | D14: =IF($A14="","",SUMIFS('Sales Log'!$J$4:$J$503,'Sales Log'!$B$4:$B$503,$A14)) | E14: =IF($A14="","",SUMIFS('Sales Log'!$L$4:$L$503,'Sales Log'!$B$4:$B$503,$A14)) | F14: =IF($A14="","",D14-E14) | G14: =IF(N(D14)>0,F14/D14,"") | H14: =IF($A14="","",SUMIFS('Sales Log'!$P$4:$P$503,'Sales Log'!$B$4:$B$503,$A14)) | I14: =IF($A14="","",IFERROR(INDEX(Shows!$O$4:$O$23,MATCH($A14,Shows!$A$4:$A$23,0)),0)) | J14: =IF($A14="","",F14-H14-I14) | K14: =IF(N(G14)>0,(I14+H14)/G14,"") | L14: =IF($A14="","",SUMIFS('Sales Log'!$K$4:$K$503,'Sales Log'!$B$4:$B$503,$A14)) | M14: =IF($A14="","",SUMIFS('Sales Log'!$Q$4:$Q$503,'Sales Log'!$B$4:$B$503,$A14,'Sales Log'!$N$4:$N$503,"Cash")) | N14: =IF($A14="","",SUMIFS('Sales Log'!$Q$4:$Q$503,'Sales Log'!$B$4:$B$503,$A14,'Sales Log'!$N$4:$N$503,"Zelle")) | O14: =IF($A14="","",SUMIFS('Sales Log'!$Q$4:$Q$503,'Sales Log'!$B$4:$B$503,$A14,'Sales Log'!$N$4:$N$503,"Venmo")) | P14: =IF($A14="","",SUMIFS('Sales Log'!$Q$4:$Q$503,'Sales Log'!$B$4:$B$503,$A14,'Sales Log'!$N$4:$N$503,"Card")) | Q14: =IF($A14="","",SUMIFS('Sales Log'!$Q$4:$Q$503,'Sales Log'!$B$4:$B$503,$A14,'Sales Log'!$N$4:$N$503,"Check")) | R14: =IF($A14="","",SUMIFS('Sales Log'!$Q$4:$Q$503,'Sales Log'!$B$4:$B$503,$A14,'Sales Log'!$N$4:$N$503,"Trade"))
A15: =IF(Shows!$A$15="","",Shows!$A$15) | B15: =IF($A15="","",COUNTIFS('Sales Log'!$B$4:$B$503,$A15)) | C15: =IF($A15="","",SUMIFS('Sales Log'!$E$4:$E$503,'Sales Log'!$B$4:$B$503,$A15)) | D15: =IF($A15="","",SUMIFS('Sales Log'!$J$4:$J$503,'Sales Log'!$B$4:$B$503,$A15)) | E15: =IF($A15="","",SUMIFS('Sales Log'!$L$4:$L$503,'Sales Log'!$B$4:$B$503,$A15)) | F15: =IF($A15="","",D15-E15) | G15: =IF(N(D15)>0,F15/D15,"") | H15: =IF($A15="","",SUMIFS('Sales Log'!$P$4:$P$503,'Sales Log'!$B$4:$B$503,$A15)) | I15: =IF($A15="","",IFERROR(INDEX(Shows!$O$4:$O$23,MATCH($A15,Shows!$A$4:$A$23,0)),0)) | J15: =IF($A15="","",F15-H15-I15) | K15: =IF(N(G15)>0,(I15+H15)/G15,"") | L15: =IF($A15="","",SUMIFS('Sales Log'!$K$4:$K$503,'Sales Log'!$B$4:$B$503,$A15)) | M15: =IF($A15="","",SUMIFS('Sales Log'!$Q$4:$Q$503,'Sales Log'!$B$4:$B$503,$A15,'Sales Log'!$N$4:$N$503,"Cash")) | N15: =IF($A15="","",SUMIFS('Sales Log'!$Q$4:$Q$503,'Sales Log'!$B$4:$B$503,$A15,'Sales Log'!$N$4:$N$503,"Zelle")) | O15: =IF($A15="","",SUMIFS('Sales Log'!$Q$4:$Q$503,'Sales Log'!$B$4:$B$503,$A15,'Sales Log'!$N$4:$N$503,"Venmo")) | P15: =IF($A15="","",SUMIFS('Sales Log'!$Q$4:$Q$503,'Sales Log'!$B$4:$B$503,$A15,'Sales Log'!$N$4:$N$503,"Card")) | Q15: =IF($A15="","",SUMIFS('Sales Log'!$Q$4:$Q$503,'Sales Log'!$B$4:$B$503,$A15,'Sales Log'!$N$4:$N$503,"Check")) | R15: =IF($A15="","",SUMIFS('Sales Log'!$Q$4:$Q$503,'Sales Log'!$B$4:$B$503,$A15,'Sales Log'!$N$4:$N$503,"Trade"))
A16: =IF(Shows!$A$16="","",Shows!$A$16) | B16: =IF($A16="","",COUNTIFS('Sales Log'!$B$4:$B$503,$A16)) | C16: =IF($A16="","",SUMIFS('Sales Log'!$E$4:$E$503,'Sales Log'!$B$4:$B$503,$A16)) | D16: =IF($A16="","",SUMIFS('Sales Log'!$J$4:$J$503,'Sales Log'!$B$4:$B$503,$A16)) | E16: =IF($A16="","",SUMIFS('Sales Log'!$L$4:$L$503,'Sales Log'!$B$4:$B$503,$A16)) | F16: =IF($A16="","",D16-E16) | G16: =IF(N(D16)>0,F16/D16,"") | H16: =IF($A16="","",SUMIFS('Sales Log'!$P$4:$P$503,'Sales Log'!$B$4:$B$503,$A16)) | I16: =IF($A16="","",IFERROR(INDEX(Shows!$O$4:$O$23,MATCH($A16,Shows!$A$4:$A$23,0)),0)) | J16: =IF($A16="","",F16-H16-I16) | K16: =IF(N(G16)>0,(I16+H16)/G16,"") | L16: =IF($A16="","",SUMIFS('Sales Log'!$K$4:$K$503,'Sales Log'!$B$4:$B$503,$A16)) | M16: =IF($A16="","",SUMIFS('Sales Log'!$Q$4:$Q$503,'Sales Log'!$B$4:$B$503,$A16,'Sales Log'!$N$4:$N$503,"Cash")) | N16: =IF($A16="","",SUMIFS('Sales Log'!$Q$4:$Q$503,'Sales Log'!$B$4:$B$503,$A16,'Sales Log'!$N$4:$N$503,"Zelle")) | O16: =IF($A16="","",SUMIFS('Sales Log'!$Q$4:$Q$503,'Sales Log'!$B$4:$B$503,$A16,'Sales Log'!$N$4:$N$503,"Venmo")) | P16: =IF($A16="","",SUMIFS('Sales Log'!$Q$4:$Q$503,'Sales Log'!$B$4:$B$503,$A16,'Sales Log'!$N$4:$N$503,"Card")) | Q16: =IF($A16="","",SUMIFS('Sales Log'!$Q$4:$Q$503,'Sales Log'!$B$4:$B$503,$A16,'Sales Log'!$N$4:$N$503,"Check")) | R16: =IF($A16="","",SUMIFS('Sales Log'!$Q$4:$Q$503,'Sales Log'!$B$4:$B$503,$A16,'Sales Log'!$N$4:$N$503,"Trade"))
A17: =IF(Shows!$A$17="","",Shows!$A$17) | B17: =IF($A17="","",COUNTIFS('Sales Log'!$B$4:$B$503,$A17)) | C17: =IF($A17="","",SUMIFS('Sales Log'!$E$4:$E$503,'Sales Log'!$B$4:$B$503,$A17)) | D17: =IF($A17="","",SUMIFS('Sales Log'!$J$4:$J$503,'Sales Log'!$B$4:$B$503,$A17)) | E17: =IF($A17="","",SUMIFS('Sales Log'!$L$4:$L$503,'Sales Log'!$B$4:$B$503,$A17)) | F17: =IF($A17="","",D17-E17) | G17: =IF(N(D17)>0,F17/D17,"") | H17: =IF($A17="","",SUMIFS('Sales Log'!$P$4:$P$503,'Sales Log'!$B$4:$B$503,$A17)) | I17: =IF($A17="","",IFERROR(INDEX(Shows!$O$4:$O$23,MATCH($A17,Shows!$A$4:$A$23,0)),0)) | J17: =IF($A17="","",F17-H17-I17) | K17: =IF(N(G17)>0,(I17+H17)/G17,"") | L17: =IF($A17="","",SUMIFS('Sales Log'!$K$4:$K$503,'Sales Log'!$B$4:$B$503,$A17)) | M17: =IF($A17="","",SUMIFS('Sales Log'!$Q$4:$Q$503,'Sales Log'!$B$4:$B$503,$A17,'Sales Log'!$N$4:$N$503,"Cash")) | N17: =IF($A17="","",SUMIFS('Sales Log'!$Q$4:$Q$503,'Sales Log'!$B$4:$B$503,$A17,'Sales Log'!$N$4:$N$503,"Zelle")) | O17: =IF($A17="","",SUMIFS('Sales Log'!$Q$4:$Q$503,'Sales Log'!$B$4:$B$503,$A17,'Sales Log'!$N$4:$N$503,"Venmo")) | P17: =IF($A17="","",SUMIFS('Sales Log'!$Q$4:$Q$503,'Sales Log'!$B$4:$B$503,$A17,'Sales Log'!$N$4:$N$503,"Card")) | Q17: =IF($A17="","",SUMIFS('Sales Log'!$Q$4:$Q$503,'Sales Log'!$B$4:$B$503,$A17,'Sales Log'!$N$4:$N$503,"Check")) | R17: =IF($A17="","",SUMIFS('Sales Log'!$Q$4:$Q$503,'Sales Log'!$B$4:$B$503,$A17,'Sales Log'!$N$4:$N$503,"Trade"))
A18: =IF(Shows!$A$18="","",Shows!$A$18) | B18: =IF($A18="","",COUNTIFS('Sales Log'!$B$4:$B$503,$A18)) | C18: =IF($A18="","",SUMIFS('Sales Log'!$E$4:$E$503,'Sales Log'!$B$4:$B$503,$A18)) | D18: =IF($A18="","",SUMIFS('Sales Log'!$J$4:$J$503,'Sales Log'!$B$4:$B$503,$A18)) | E18: =IF($A18="","",SUMIFS('Sales Log'!$L$4:$L$503,'Sales Log'!$B$4:$B$503,$A18)) | F18: =IF($A18="","",D18-E18) | G18: =IF(N(D18)>0,F18/D18,"") | H18: =IF($A18="","",SUMIFS('Sales Log'!$P$4:$P$503,'Sales Log'!$B$4:$B$503,$A18)) | I18: =IF($A18="","",IFERROR(INDEX(Shows!$O$4:$O$23,MATCH($A18,Shows!$A$4:$A$23,0)),0)) | J18: =IF($A18="","",F18-H18-I18) | K18: =IF(N(G18)>0,(I18+H18)/G18,"") | L18: =IF($A18="","",SUMIFS('Sales Log'!$K$4:$K$503,'Sales Log'!$B$4:$B$503,$A18)) | M18: =IF($A18="","",SUMIFS('Sales Log'!$Q$4:$Q$503,'Sales Log'!$B$4:$B$503,$A18,'Sales Log'!$N$4:$N$503,"Cash")) | N18: =IF($A18="","",SUMIFS('Sales Log'!$Q$4:$Q$503,'Sales Log'!$B$4:$B$503,$A18,'Sales Log'!$N$4:$N$503,"Zelle")) | O18: =IF($A18="","",SUMIFS('Sales Log'!$Q$4:$Q$503,'Sales Log'!$B$4:$B$503,$A18,'Sales Log'!$N$4:$N$503,"Venmo")) | P18: =IF($A18="","",SUMIFS('Sales Log'!$Q$4:$Q$503,'Sales Log'!$B$4:$B$503,$A18,'Sales Log'!$N$4:$N$503,"Card")) | Q18: =IF($A18="","",SUMIFS('Sales Log'!$Q$4:$Q$503,'Sales Log'!$B$4:$B$503,$A18,'Sales Log'!$N$4:$N$503,"Check")) | R18: =IF($A18="","",SUMIFS('Sales Log'!$Q$4:$Q$503,'Sales Log'!$B$4:$B$503,$A18,'Sales Log'!$N$4:$N$503,"Trade"))
A19: =IF(Shows!$A$19="","",Shows!$A$19) | B19: =IF($A19="","",COUNTIFS('Sales Log'!$B$4:$B$503,$A19)) | C19: =IF($A19="","",SUMIFS('Sales Log'!$E$4:$E$503,'Sales Log'!$B$4:$B$503,$A19)) | D19: =IF($A19="","",SUMIFS('Sales Log'!$J$4:$J$503,'Sales Log'!$B$4:$B$503,$A19)) | E19: =IF($A19="","",SUMIFS('Sales Log'!$L$4:$L$503,'Sales Log'!$B$4:$B$503,$A19)) | F19: =IF($A19="","",D19-E19) | G19: =IF(N(D19)>0,F19/D19,"") | H19: =IF($A19="","",SUMIFS('Sales Log'!$P$4:$P$503,'Sales Log'!$B$4:$B$503,$A19)) | I19: =IF($A19="","",IFERROR(INDEX(Shows!$O$4:$O$23,MATCH($A19,Shows!$A$4:$A$23,0)),0)) | J19: =IF($A19="","",F19-H19-I19) | K19: =IF(N(G19)>0,(I19+H19)/G19,"") | L19: =IF($A19="","",SUMIFS('Sales Log'!$K$4:$K$503,'Sales Log'!$B$4:$B$503,$A19)) | M19: =IF($A19="","",SUMIFS('Sales Log'!$Q$4:$Q$503,'Sales Log'!$B$4:$B$503,$A19,'Sales Log'!$N$4:$N$503,"Cash")) | N19: =IF($A19="","",SUMIFS('Sales Log'!$Q$4:$Q$503,'Sales Log'!$B$4:$B$503,$A19,'Sales Log'!$N$4:$N$503,"Zelle")) | O19: =IF($A19="","",SUMIFS('Sales Log'!$Q$4:$Q$503,'Sales Log'!$B$4:$B$503,$A19,'Sales Log'!$N$4:$N$503,"Venmo")) | P19: =IF($A19="","",SUMIFS('Sales Log'!$Q$4:$Q$503,'Sales Log'!$B$4:$B$503,$A19,'Sales Log'!$N$4:$N$503,"Card")) | Q19: =IF($A19="","",SUMIFS('Sales Log'!$Q$4:$Q$503,'Sales Log'!$B$4:$B$503,$A19,'Sales Log'!$N$4:$N$503,"Check")) | R19: =IF($A19="","",SUMIFS('Sales Log'!$Q$4:$Q$503,'Sales Log'!$B$4:$B$503,$A19,'Sales Log'!$N$4:$N$503,"Trade"))
A20: =IF(Shows!$A$20="","",Shows!$A$20) | B20: =IF($A20="","",COUNTIFS('Sales Log'!$B$4:$B$503,$A20)) | C20: =IF($A20="","",SUMIFS('Sales Log'!$E$4:$E$503,'Sales Log'!$B$4:$B$503,$A20)) | D20: =IF($A20="","",SUMIFS('Sales Log'!$J$4:$J$503,'Sales Log'!$B$4:$B$503,$A20)) | E20: =IF($A20="","",SUMIFS('Sales Log'!$L$4:$L$503,'Sales Log'!$B$4:$B$503,$A20)) | F20: =IF($A20="","",D20-E20) | G20: =IF(N(D20)>0,F20/D20,"") | H20: =IF($A20="","",SUMIFS('Sales Log'!$P$4:$P$503,'Sales Log'!$B$4:$B$503,$A20)) | I20: =IF($A20="","",IFERROR(INDEX(Shows!$O$4:$O$23,MATCH($A20,Shows!$A$4:$A$23,0)),0)) | J20: =IF($A20="","",F20-H20-I20) | K20: =IF(N(G20)>0,(I20+H20)/G20,"") | L20: =IF($A20="","",SUMIFS('Sales Log'!$K$4:$K$503,'Sales Log'!$B$4:$B$503,$A20)) | M20: =IF($A20="","",SUMIFS('Sales Log'!$Q$4:$Q$503,'Sales Log'!$B$4:$B$503,$A20,'Sales Log'!$N$4:$N$503,"Cash")) | N20: =IF($A20="","",SUMIFS('Sales Log'!$Q$4:$Q$503,'Sales Log'!$B$4:$B$503,$A20,'Sales Log'!$N$4:$N$503,"Zelle")) | O20: =IF($A20="","",SUMIFS('Sales Log'!$Q$4:$Q$503,'Sales Log'!$B$4:$B$503,$A20,'Sales Log'!$N$4:$N$503,"Venmo")) | P20: =IF($A20="","",SUMIFS('Sales Log'!$Q$4:$Q$503,'Sales Log'!$B$4:$B$503,$A20,'Sales Log'!$N$4:$N$503,"Card")) | Q20: =IF($A20="","",SUMIFS('Sales Log'!$Q$4:$Q$503,'Sales Log'!$B$4:$B$503,$A20,'Sales Log'!$N$4:$N$503,"Check")) | R20: =IF($A20="","",SUMIFS('Sales Log'!$Q$4:$Q$503,'Sales Log'!$B$4:$B$503,$A20,'Sales Log'!$N$4:$N$503,"Trade"))
A21: =IF(Shows!$A$21="","",Shows!$A$21) | B21: =IF($A21="","",COUNTIFS('Sales Log'!$B$4:$B$503,$A21)) | C21: =IF($A21="","",SUMIFS('Sales Log'!$E$4:$E$503,'Sales Log'!$B$4:$B$503,$A21)) | D21: =IF($A21="","",SUMIFS('Sales Log'!$J$4:$J$503,'Sales Log'!$B$4:$B$503,$A21)) | E21: =IF($A21="","",SUMIFS('Sales Log'!$L$4:$L$503,'Sales Log'!$B$4:$B$503,$A21)) | F21: =IF($A21="","",D21-E21) | G21: =IF(N(D21)>0,F21/D21,"") | H21: =IF($A21="","",SUMIFS('Sales Log'!$P$4:$P$503,'Sales Log'!$B$4:$B$503,$A21)) | I21: =IF($A21="","",IFERROR(INDEX(Shows!$O$4:$O$23,MATCH($A21,Shows!$A$4:$A$23,0)),0)) | J21: =IF($A21="","",F21-H21-I21) | K21: =IF(N(G21)>0,(I21+H21)/G21,"") | L21: =IF($A21="","",SUMIFS('Sales Log'!$K$4:$K$503,'Sales Log'!$B$4:$B$503,$A21)) | M21: =IF($A21="","",SUMIFS('Sales Log'!$Q$4:$Q$503,'Sales Log'!$B$4:$B$503,$A21,'Sales Log'!$N$4:$N$503,"Cash")) | N21: =IF($A21="","",SUMIFS('Sales Log'!$Q$4:$Q$503,'Sales Log'!$B$4:$B$503,$A21,'Sales Log'!$N$4:$N$503,"Zelle")) | O21: =IF($A21="","",SUMIFS('Sales Log'!$Q$4:$Q$503,'Sales Log'!$B$4:$B$503,$A21,'Sales Log'!$N$4:$N$503,"Venmo")) | P21: =IF($A21="","",SUMIFS('Sales Log'!$Q$4:$Q$503,'Sales Log'!$B$4:$B$503,$A21,'Sales Log'!$N$4:$N$503,"Card")) | Q21: =IF($A21="","",SUMIFS('Sales Log'!$Q$4:$Q$503,'Sales Log'!$B$4:$B$503,$A21,'Sales Log'!$N$4:$N$503,"Check")) | R21: =IF($A21="","",SUMIFS('Sales Log'!$Q$4:$Q$503,'Sales Log'!$B$4:$B$503,$A21,'Sales Log'!$N$4:$N$503,"Trade"))
A22: =IF(Shows!$A$22="","",Shows!$A$22) | B22: =IF($A22="","",COUNTIFS('Sales Log'!$B$4:$B$503,$A22)) | C22: =IF($A22="","",SUMIFS('Sales Log'!$E$4:$E$503,'Sales Log'!$B$4:$B$503,$A22)) | D22: =IF($A22="","",SUMIFS('Sales Log'!$J$4:$J$503,'Sales Log'!$B$4:$B$503,$A22)) | E22: =IF($A22="","",SUMIFS('Sales Log'!$L$4:$L$503,'Sales Log'!$B$4:$B$503,$A22)) | F22: =IF($A22="","",D22-E22) | G22: =IF(N(D22)>0,F22/D22,"") | H22: =IF($A22="","",SUMIFS('Sales Log'!$P$4:$P$503,'Sales Log'!$B$4:$B$503,$A22)) | I22: =IF($A22="","",IFERROR(INDEX(Shows!$O$4:$O$23,MATCH($A22,Shows!$A$4:$A$23,0)),0)) | J22: =IF($A22="","",F22-H22-I22) | K22: =IF(N(G22)>0,(I22+H22)/G22,"") | L22: =IF($A22="","",SUMIFS('Sales Log'!$K$4:$K$503,'Sales Log'!$B$4:$B$503,$A22)) | M22: =IF($A22="","",SUMIFS('Sales Log'!$Q$4:$Q$503,'Sales Log'!$B$4:$B$503,$A22,'Sales Log'!$N$4:$N$503,"Cash")) | N22: =IF($A22="","",SUMIFS('Sales Log'!$Q$4:$Q$503,'Sales Log'!$B$4:$B$503,$A22,'Sales Log'!$N$4:$N$503,"Zelle")) | O22: =IF($A22="","",SUMIFS('Sales Log'!$Q$4:$Q$503,'Sales Log'!$B$4:$B$503,$A22,'Sales Log'!$N$4:$N$503,"Venmo")) | P22: =IF($A22="","",SUMIFS('Sales Log'!$Q$4:$Q$503,'Sales Log'!$B$4:$B$503,$A22,'Sales Log'!$N$4:$N$503,"Card")) | Q22: =IF($A22="","",SUMIFS('Sales Log'!$Q$4:$Q$503,'Sales Log'!$B$4:$B$503,$A22,'Sales Log'!$N$4:$N$503,"Check")) | R22: =IF($A22="","",SUMIFS('Sales Log'!$Q$4:$Q$503,'Sales Log'!$B$4:$B$503,$A22,'Sales Log'!$N$4:$N$503,"Trade"))
A23: =IF(Shows!$A$23="","",Shows!$A$23) | B23: =IF($A23="","",COUNTIFS('Sales Log'!$B$4:$B$503,$A23)) | C23: =IF($A23="","",SUMIFS('Sales Log'!$E$4:$E$503,'Sales Log'!$B$4:$B$503,$A23)) | D23: =IF($A23="","",SUMIFS('Sales Log'!$J$4:$J$503,'Sales Log'!$B$4:$B$503,$A23)) | E23: =IF($A23="","",SUMIFS('Sales Log'!$L$4:$L$503,'Sales Log'!$B$4:$B$503,$A23)) | F23: =IF($A23="","",D23-E23) | G23: =IF(N(D23)>0,F23/D23,"") | H23: =IF($A23="","",SUMIFS('Sales Log'!$P$4:$P$503,'Sales Log'!$B$4:$B$503,$A23)) | I23: =IF($A23="","",IFERROR(INDEX(Shows!$O$4:$O$23,MATCH($A23,Shows!$A$4:$A$23,0)),0)) | J23: =IF($A23="","",F23-H23-I23) | K23: =IF(N(G23)>0,(I23+H23)/G23,"") | L23: =IF($A23="","",SUMIFS('Sales Log'!$K$4:$K$503,'Sales Log'!$B$4:$B$503,$A23)) | M23: =IF($A23="","",SUMIFS('Sales Log'!$Q$4:$Q$503,'Sales Log'!$B$4:$B$503,$A23,'Sales Log'!$N$4:$N$503,"Cash")) | N23: =IF($A23="","",SUMIFS('Sales Log'!$Q$4:$Q$503,'Sales Log'!$B$4:$B$503,$A23,'Sales Log'!$N$4:$N$503,"Zelle")) | O23: =IF($A23="","",SUMIFS('Sales Log'!$Q$4:$Q$503,'Sales Log'!$B$4:$B$503,$A23,'Sales Log'!$N$4:$N$503,"Venmo")) | P23: =IF($A23="","",SUMIFS('Sales Log'!$Q$4:$Q$503,'Sales Log'!$B$4:$B$503,$A23,'Sales Log'!$N$4:$N$503,"Card")) | Q23: =IF($A23="","",SUMIFS('Sales Log'!$Q$4:$Q$503,'Sales Log'!$B$4:$B$503,$A23,'Sales Log'!$N$4:$N$503,"Check")) | R23: =IF($A23="","",SUMIFS('Sales Log'!$Q$4:$Q$503,'Sales Log'!$B$4:$B$503,$A23,'Sales Log'!$N$4:$N$503,"Trade"))
A24: SEASON TOTAL | B24: =SUM(B4:B23) | C24: =SUM(C4:C23) | D24: =SUM(D4:D23) | E24: =SUM(E4:E23) | F24: =SUM(F4:F23) | G24: =IF(N(D24)>0,F24/D24,"") | H24: =SUM(H4:H23) | I24: =SUM(I4:I23) | J24: =SUM(J4:J23) | K24: =IF(N(G24)>0,(I24+H24)/G24,"") | L24: =SUM(L4:L23) | M24: =SUM(M4:M23) | N24: =SUM(N4:N23) | O24: =SUM(O4:O23) | P24: =SUM(P4:P23) | Q24: =SUM(Q4:Q23) | R24: =SUM(R4:R23)
A27: Inventory position | D27: Read this before the next show
A28: SKUs listed | B28: =COUNTA(Inventory!$A$4:$A$253) | D28: • NET PROFIT is what you keep after cost of goods, card fees, table, travel, hotel and meals.
A29: Units brought | B29: =SUM(Inventory!$M$4:$M$253) | D29: • Break-even revenue is what you must sell, at your current margin, just to cover the show.
A30: Units sold | B30: =SUM(Inventory!$N$4:$N$253) | D30: • Sales tax collected is owed to the state. Set it aside; it is not income.
A31: Units left | B31: =SUM(Inventory!$O$4:$O$253) | D31: • Cash / Zelle / Venmo / Card columns are your end-of-day reconciliation — count against them nightly.
A32: Cost still on the table | B32: =SUMIF(Inventory!$O$4:$O$253,">0",Inventory!$S$4:$S$253) | D32: • Sell-through under ~40% usually means you brought too much, or priced too high.
A33: Retail still on the table | B33: =SUMIF(Inventory!$O$4:$O$253,">0",Inventory!$T$4:$T$253)
A34: Sell-through rate | B34: =IFERROR(SUM(Inventory!$N$4:$N$253)/SUM(Inventory!$M$4:$M$253),"")

Sheet Inventory
A1: Inventory — every SKU you put on the table
A2: Blue = you type it. Black = calculated, do not overwrite. Qty sold reads the Sales Log automatically. Floor price is the lowest you will accept when someone haggles.
A3: SKU | B3: Brand | C3: Model | D3: Variant / finish | E3: Nib | F3: Category | G3: Condition | H3: Landed cost | I3: MSRP | J3: Show price | K3: Floor price | L3: Dealer price | M3: Qty brought | N3: Qty sold | O3: Qty left | P3: Margin @ price | Q3: Margin @ floor | R3: Profit / unit | S3: Cost tied up | T3: Retail value | U3: Case / tray | V3: Serial / lot | W3: Tags | X3: Photo link | Y3: Notes
A4: SAI-PROGEAR-M | B4: Sailor | C4: Pro Gear Slim | D4: Sky Blue | E4: M | F4: Pen | G4: New | H4: 168 | I4: 340 | J4: 340 | K4: 290 | L4: 255 | M4: 3 | N4: =IF($A4="","",IFERROR(SUMIFS('Sales Log'!$E$4:$E$503,'Sales Log'!$C$4:$C$503,$A4),0)) | O4: =IF($A4="","",M4-N4) | P4: =IF(J4>0,(J4-H4)/J4,"") | Q4: =IF(K4>0,(K4-H4)/K4,"") | R4: =IF($A4="","",J4-H4) | S4: =IF($A4="","",O4*H4) | T4: =IF($A4="","",O4*J4) | U4: Case 1, tray B | W4: limited, japan | Y4: EXAMPLE ROW — overwrite or delete it
N5: =IF($A5="","",IFERROR(SUMIFS('Sales Log'!$E$4:$E$503,'Sales Log'!$C$4:$C$503,$A5),0)) | O5: =IF($A5="","",M5-N5) | P5: =IF(J5>0,(J5-H5)/J5,"") | Q5: =IF(K5>0,(K5-H5)/K5,"") | R5: =IF($A5="","",J5-H5) | S5: =IF($A5="","",O5*H5) | T5: =IF($A5="","",O5*J5)
N6: =IF($A6="","",IFERROR(SUMIFS('Sales Log'!$E$4:$E$503,'Sales Log'!$C$4:$C$503,$A6),0)) | O6: =IF($A6="","",M6-N6) | P6: =IF(J6>0,(J6-H6)/J6,"") | Q6: =IF(K6>0,(K6-H6)/K6,"") | R6: =IF($A6="","",J6-H6) | S6: =IF($A6="","",O6*H6) | T6: =IF($A6="","",O6*J6)
N7: =IF($A7="","",IFERROR(SUMIFS('Sales Log'!$E$4:$E$503,'Sales Log'!$C$4:$C$503,$A7),0)) | O7: =IF($A7="","",M7-N7) | P7: =IF(J7>0,(J7-H7)/J7,"") | Q7: =IF(K7>0,(K7-H7)/K7,"") | R7: =IF($A7="","",J7-H7) | S7: =IF($A7="","",O7*H7) | T7: =IF($A7="","",O7*J7)
N8: =IF($A8="","",IFERROR(SUMIFS('Sales Log'!$E$4:$E$503,'Sales Log'!$C$4:$C$503,$A8),0)) | O8: =IF($A8="","",M8-N8) | P8: =IF(J8>0,(J8-H8)/J8,"") | Q8: =IF(K8>0,(K8-H8)/K8,"") | R8: =IF($A8="","",J8-H8) | S8: =IF($A8="","",O8*H8) | T8: =IF($A8="","",O8*J8)
N9: =IF($A9="","",IFERROR(SUMIFS('Sales Log'!$E$4:$E$503,'Sales Log'!$C$4:$C$503,$A9),0)) | O9: =IF($A9="","",M9-N9) | P9: =IF(J9>0,(J9-H9)/J9,"") | Q9: =IF(K9>0,(K9-H9)/K9,"") | R9: =IF($A9="","",J9-H9) | S9: =IF($A9="","",O9*H9) | T9: =IF($A9="","",O9*J9)
N10: =IF($A10="","",IFERROR(SUMIFS('Sales Log'!$E$4:$E$503,'Sales Log'!$C$4:$C$503,$A10),0)) | O10: =IF($A10="","",M10-N10) | P10: =IF(J10>0,(J10-H10)/J10,"") | Q10: =IF(K10>0,(K10-H10)/K10,"") | R10: =IF($A10="","",J10-H10) | S10: =IF($A10="","",O10*H10) | T10: =IF($A10="","",O10*J10)
N11: =IF($A11="","",IFERROR(SUMIFS('Sales Log'!$E$4:$E$503,'Sales Log'!$C$4:$C$503,$A11),0)) | O11: =IF($A11="","",M11-N11) | P11: =IF(J11>0,(J11-H11)/J11,"") | Q11: =IF(K11>0,(K11-H11)/K11,"") | R11: =IF($A11="","",J11-H11) | S11: =IF($A11="","",O11*H11) | T11: =IF($A11="","",O11*J11)
N12: =IF($A12="","",IFERROR(SUMIFS('Sales Log'!$E$4:$E$503,'Sales Log'!$C$4:$C$503,$A12),0)) | O12: =IF($A12="","",M12-N12) | P12: =IF(J12>0,(J12-H12)/J12,"") | Q12: =IF(K12>0,(K12-H12)/K12,"") | R12: =IF($A12="","",J12-H12) | S12: =IF($A12="","",O12*H12) | T12: =IF($A12="","",O12*J12)
N13: =IF($A13="","",IFERROR(SUMIFS('Sales Log'!$E$4:$E$503,'Sales Log'!$C$4:$C$503,$A13),0)) | O13: =IF($A13="","",M13-N13) | P13: =IF(J13>0,(J13-H13)/J13,"") | Q13: =IF(K13>0,(K13-H13)/K13,"") | R13: =IF($A13="","",J13-H13) | S13: =IF($A13="","",O13*H13) | T13: =IF($A13="","",O13*J13)
N14: =IF($A14="","",IFERROR(SUMIFS('Sales Log'!$E$4:$E$503,'Sales Log'!$C$4:$C$503,$A14),0)) | O14: =IF($A14="","",M14-N14) | P14: =IF(J14>0,(J14-H14)/J14,"") | Q14: =IF(K14>0,(K14-H14)/K14,"") | R14: =IF($A14="","",J14-H14) | S14: =IF($A14="","",O14*H14) | T14: =IF($A14="","",O14*J14)
N15: =IF($A15="","",IFERROR(SUMIFS('Sales Log'!$E$4:$E$503,'Sales Log'!$C$4:$C$503,$A15),0)) | O15: =IF($A15="","",M15-N15) | P15: =IF(J15>0,(J15-H15)/J15,"") | Q15: =IF(K15>0,(K15-H15)/K15,"") | R15: =IF($A15="","",J15-H15) | S15: =IF($A15="","",O15*H15) | T15: =IF($A15="","",O15*J15)
N16: =IF($A16="","",IFERROR(SUMIFS('Sales Log'!$E$4:$E$503,'Sales Log'!$C$4:$C$503,$A16),0)) | O16: =IF($A16="","",M16-N16) | P16: =IF(J16>0,(J16-H16)/J16,"") | Q16: =IF(K16>0,(K16-H16)/K16,"") | R16: =IF($A16="","",J16-H16) | S16: =IF($A16="","",O16*H16) | T16: =IF($A16="","",O16*J16)
... N253: =IF($A253="","",IFERROR(SUMIFS('Sales Log'!$E$4:$E$503,'Sales Log'!$C$4:$C$503,$A253),0)) | O253: =IF($A253="","",M253-N253) | P253: =IF(J253>0,(J253-H253)/J253,"") | Q253: =IF(K253>0,(K253-H253)/K253,"") | R253: =IF($A253="","",J253-H253) | S253: =IF($A253="","",O253*H253) | T253: =IF($A253="","",O253*J253)

Sheet Sales Log
A1: Sales Log — one row per item sold
A2: Type SKU and the item name and cost fill themselves in. One row per line item: a customer buying three pens is three rows, same date and payment method.
A3: Date | B3: Show | C3: SKU | D3: Item (auto) | E3: Qty | F3: Unit price | G3: Discount $ | H3: Unit cost (auto) | I3: Taxable | J3: Line revenue | K3: Sales tax | L3: Line COGS | M3: Line profit | N3: Payment method | O3: Payment ref | P3: Card fee | Q3: Net to you | R3: Customer | S3: Email / phone | T3: Notes
D4: =IF($C4="","",IFERROR(INDEX(Inventory!$B$4:$B$253,MATCH($C4,Inventory!$A$4:$A$253,0))&" "&INDEX(Inventory!$C$4:$C$253,MATCH($C4,Inventory!$A$4:$A$253,0)),"SKU not in Inventory")) | H4: =IF($C4="","",IFERROR(INDEX(Inventory!$H$4:$H$253,MATCH($C4,Inventory!$A$4:$A$253,0)),0)) | J4: =IF($C4="","",MAX(0,$E4*$F4-$G4)) | K4: =IF(OR($C4="",$I4="No"),0,ROUND($J4*IFERROR(INDEX(Shows!$F$4:$F$23,MATCH($B4,Shows!$A$4:$A$23,0)),0),2)) | L4: =IF($C4="","",$E4*$H4) | M4: =IF($C4="","",$J4-$L4-$P4) | P4: =IF(OR($C4="",$N4<>"Card"),0,ROUND(($J4+$K4)*IFERROR(INDEX(Shows!$G$4:$G$23,MATCH($B4,Shows!$A$4:$A$23,0)),0)+IFERROR(INDEX(Shows!$H$4:$H$23,MATCH($B4,Shows!$A$4:$A$23,0)),0),2)) | Q4: =IF($C4="","",$J4+$K4-$P4)
D5: =IF($C5="","",IFERROR(INDEX(Inventory!$B$4:$B$253,MATCH($C5,Inventory!$A$4:$A$253,0))&" "&INDEX(Inventory!$C$4:$C$253,MATCH($C5,Inventory!$A$4:$A$253,0)),"SKU not in Inventory")) | H5: =IF($C5="","",IFERROR(INDEX(Inventory!$H$4:$H$253,MATCH($C5,Inventory!$A$4:$A$253,0)),0)) | J5: =IF($C5="","",MAX(0,$E5*$F5-$G5)) | K5: =IF(OR($C5="",$I5="No"),0,ROUND($J5*IFERROR(INDEX(Shows!$F$4:$F$23,MATCH($B5,Shows!$A$4:$A$23,0)),0),2)) | L5: =IF($C5="","",$E5*$H5) | M5: =IF($C5="","",$J5-$L5-$P5) | P5: =IF(OR($C5="",$N5<>"Card"),0,ROUND(($J5+$K5)*IFERROR(INDEX(Shows!$G$4:$G$23,MATCH($B5,Shows!$A$4:$A$23,0)),0)+IFERROR(INDEX(Shows!$H$4:$H$23,MATCH($B5,Shows!$A$4:$A$23,0)),0),2)) | Q5: =IF($C5="","",$J5+$K5-$P5)
D6: =IF($C6="","",IFERROR(INDEX(Inventory!$B$4:$B$253,MATCH($C6,Inventory!$A$4:$A$253,0))&" "&INDEX(Inventory!$C$4:$C$253,MATCH($C6,Inventory!$A$4:$A$253,0)),"SKU not in Inventory")) | H6: =IF($C6="","",IFERROR(INDEX(Inventory!$H$4:$H$253,MATCH($C6,Inventory!$A$4:$A$253,0)),0)) | J6: =IF($C6="","",MAX(0,$E6*$F6-$G6)) | K6: =IF(OR($C6="",$I6="No"),0,ROUND($J6*IFERROR(INDEX(Shows!$F$4:$F$23,MATCH($B6,Shows!$A$4:$A$23,0)),0),2)) | L6: =IF($C6="","",$E6*$H6) | M6: =IF($C6="","",$J6-$L6-$P6) | P6: =IF(OR($C6="",$N6<>"Card"),0,ROUND(($J6+$K6)*IFERROR(INDEX(Shows!$G$4:$G$23,MATCH($B6,Shows!$A$4:$A$23,0)),0)+IFERROR(INDEX(Shows!$H$4:$H$23,MATCH($B6,Shows!$A$4:$A$23,0)),0),2)) | Q6: =IF($C6="","",$J6+$K6-$P6)
D7: =IF($C7="","",IFERROR(INDEX(Inventory!$B$4:$B$253,MATCH($C7,Inventory!$A$4:$A$253,0))&" "&INDEX(Inventory!$C$4:$C$253,MATCH($C7,Inventory!$A$4:$A$253,0)),"SKU not in Inventory")) | H7: =IF($C7="","",IFERROR(INDEX(Inventory!$H$4:$H$253,MATCH($C7,Inventory!$A$4:$A$253,0)),0)) | J7: =IF($C7="","",MAX(0,$E7*$F7-$G7)) | K7: =IF(OR($C7="",$I7="No"),0,ROUND($J7*IFERROR(INDEX(Shows!$F$4:$F$23,MATCH($B7,Shows!$A$4:$A$23,0)),0),2)) | L7: =IF($C7="","",$E7*$H7) | M7: =IF($C7="","",$J7-$L7-$P7) | P7: =IF(OR($C7="",$N7<>"Card"),0,ROUND(($J7+$K7)*IFERROR(INDEX(Shows!$G$4:$G$23,MATCH($B7,Shows!$A$4:$A$23,0)),0)+IFERROR(INDEX(Shows!$H$4:$H$23,MATCH($B7,Shows!$A$4:$A$23,0)),0),2)) | Q7: =IF($C7="","",$J7+$K7-$P7)
D8: =IF($C8="","",IFERROR(INDEX(Inventory!$B$4:$B$253,MATCH($C8,Inventory!$A$4:$A$253,0))&" "&INDEX(Inventory!$C$4:$C$253,MATCH($C8,Inventory!$A$4:$A$253,0)),"SKU not in Inventory")) | H8: =IF($C8="","",IFERROR(INDEX(Inventory!$H$4:$H$253,MATCH($C8,Inventory!$A$4:$A$253,0)),0)) | J8: =IF($C8="","",MAX(0,$E8*$F8-$G8)) | K8: =IF(OR($C8="",$I8="No"),0,ROUND($J8*IFERROR(INDEX(Shows!$F$4:$F$23,MATCH($B8,Shows!$A$4:$A$23,0)),0),2)) | L8: =IF($C8="","",$E8*$H8) | M8: =IF($C8="","",$J8-$L8-$P8) | P8: =IF(OR($C8="",$N8<>"Card"),0,ROUND(($J8+$K8)*IFERROR(INDEX(Shows!$G$4:$G$23,MATCH($B8,Shows!$A$4:$A$23,0)),0)+IFERROR(INDEX(Shows!$H$4:$H$23,MATCH($B8,Shows!$A$4:$A$23,0)),0),2)) | Q8: =IF($C8="","",$J8+$K8-$P8)
D9: =IF($C9="","",IFERROR(INDEX(Inventory!$B$4:$B$253,MATCH($C9,Inventory!$A$4:$A$253,0))&" "&INDEX(Inventory!$C$4:$C$253,MATCH($C9,Inventory!$A$4:$A$253,0)),"SKU not in Inventory")) | H9: =IF($C9="","",IFERROR(INDEX(Inventory!$H$4:$H$253,MATCH($C9,Inventory!$A$4:$A$253,0)),0)) | J9: =IF($C9="","",MAX(0,$E9*$F9-$G9)) | K9: =IF(OR($C9="",$I9="No"),0,ROUND($J9*IFERROR(INDEX(Shows!$F$4:$F$23,MATCH($B9,Shows!$A$4:$A$23,0)),0),2)) | L9: =IF($C9="","",$E9*$H9) | M9: =IF($C9="","",$J9-$L9-$P9) | P9: =IF(OR($C9="",$N9<>"Card"),0,ROUND(($J9+$K9)*IFERROR(INDEX(Shows!$G$4:$G$23,MATCH($B9,Shows!$A$4:$A$23,0)),0)+IFERROR(INDEX(Shows!$H$4:$H$23,MATCH($B9,Shows!$A$4:$A$23,0)),0),2)) | Q9: =IF($C9="","",$J9+$K9-$P9)
D10: =IF($C10="","",IFERROR(INDEX(Inventory!$B$4:$B$253,MATCH($C10,Inventory!$A$4:$A$253,0))&" "&INDEX(Inventory!$C$4:$C$253,MATCH($C10,Inventory!$A$4:$A$253,0)),"SKU not in Inventory")) | H10: =IF($C10="","",IFERROR(INDEX(Inventory!$H$4:$H$253,MATCH($C10,Inventory!$A$4:$A$253,0)),0)) | J10: =IF($C10="","",MAX(0,$E10*$F10-$G10)) | K10: =IF(OR($C10="",$I10="No"),0,ROUND($J10*IFERROR(INDEX(Shows!$F$4:$F$23,MATCH($B10,Shows!$A$4:$A$23,0)),0),2)) | L10: =IF($C10="","",$E10*$H10) | M10: =IF($C10="","",$J10-$L10-$P10) | P10: =IF(OR($C10="",$N10<>"Card"),0,ROUND(($J10+$K10)*IFERROR(INDEX(Shows!$G$4:$G$23,MATCH($B10,Shows!$A$4:$A$23,0)),0)+IFERROR(INDEX(Shows!$H$4:$H$23,MATCH($B10,Shows!$A$4:$A$23,0)),0),2)) | Q10: =IF($C10="","",$J10+$K10-$P10)
D11: =IF($C11="","",IFERROR(INDEX(Inventory!$B$4:$B$253,MATCH($C11,Inventory!$A$4:$A$253,0))&" "&INDEX(Inventory!$C$4:$C$253,MATCH($C11,Inventory!$A$4:$A$253,0)),"SKU not in Inventory")) | H11: =IF($C11="","",IFERROR(INDEX(Inventory!$H$4:$H$253,MATCH($C11,Inventory!$A$4:$A$253,0)),0)) | J11: =IF($C11="","",MAX(0,$E11*$F11-$G11)) | K11: =IF(OR($C11="",$I11="No"),0,ROUND($J11*IFERROR(INDEX(Shows!$F$4:$F$23,MATCH($B11,Shows!$A$4:$A$23,0)),0),2)) | L11: =IF($C11="","",$E11*$H11) | M11: =IF($C11="","",$J11-$L11-$P11) | P11: =IF(OR($C11="",$N11<>"Card"),0,ROUND(($J11+$K11)*IFERROR(INDEX(Shows!$G$4:$G$23,MATCH($B11,Shows!$A$4:$A$23,0)),0)+IFERROR(INDEX(Shows!$H$4:$H$23,MATCH($B11,Shows!$A$4:$A$23,0)),0),2)) | Q11: =IF($C11="","",$J11+$K11-$P11)
D12: =IF($C12="","",IFERROR(INDEX(Inventory!$B$4:$B$253,MATCH($C12,Inventory!$A$4:$A$253,0))&" "&INDEX(Inventory!$C$4:$C$253,MATCH($C12,Inventory!$A$4:$A$253,0)),"SKU not in Inventory")) | H12: =IF($C12="","",IFERROR(INDEX(Inventory!$H$4:$H$253,MATCH($C12,Inventory!$A$4:$A$253,0)),0)) | J12: =IF($C12="","",MAX(0,$E12*$F12-$G12)) | K12: =IF(OR($C12="",$I12="No"),0,ROUND($J12*IFERROR(INDEX(Shows!$F$4:$F$23,MATCH($B12,Shows!$A$4:$A$23,0)),0),2)) | L12: =IF($C12="","",$E12*$H12) | M12: =IF($C12="","",$J12-$L12-$P12) | P12: =IF(OR($C12="",$N12<>"Card"),0,ROUND(($J12+$K12)*IFERROR(INDEX(Shows!$G$4:$G$23,MATCH($B12,Shows!$A$4:$A$23,0)),0)+IFERROR(INDEX(Shows!$H$4:$H$23,MATCH($B12,Shows!$A$4:$A$23,0)),0),2)) | Q12: =IF($C12="","",$J12+$K12-$P12)
D13: =IF($C13="","",IFERROR(INDEX(Inventory!$B$4:$B$253,MATCH($C13,Inventory!$A$4:$A$253,0))&" "&INDEX(Inventory!$C$4:$C$253,MATCH($C13,Inventory!$A$4:$A$253,0)),"SKU not in Inventory")) | H13: =IF($C13="","",IFERROR(INDEX(Inventory!$H$4:$H$253,MATCH($C13,Inventory!$A$4:$A$253,0)),0)) | J13: =IF($C13="","",MAX(0,$E13*$F13-$G13)) | K13: =IF(OR($C13="",$I13="No"),0,ROUND($J13*IFERROR(INDEX(Shows!$F$4:$F$23,MATCH($B13,Shows!$A$4:$A$23,0)),0),2)) | L13: =IF($C13="","",$E13*$H13) | M13: =IF($C13="","",$J13-$L13-$P13) | P13: =IF(OR($C13="",$N13<>"Card"),0,ROUND(($J13+$K13)*IFERROR(INDEX(Shows!$G$4:$G$23,MATCH($B13,Shows!$A$4:$A$23,0)),0)+IFERROR(INDEX(Shows!$H$4:$H$23,MATCH($B13,Shows!$A$4:$A$23,0)),0),2)) | Q13: =IF($C13="","",$J13+$K13-$P13)
D14: =IF($C14="","",IFERROR(INDEX(Inventory!$B$4:$B$253,MATCH($C14,Inventory!$A$4:$A$253,0))&" "&INDEX(Inventory!$C$4:$C$253,MATCH($C14,Inventory!$A$4:$A$253,0)),"SKU not in Inventory")) | H14: =IF($C14="","",IFERROR(INDEX(Inventory!$H$4:$H$253,MATCH($C14,Inventory!$A$4:$A$253,0)),0)) | J14: =IF($C14="","",MAX(0,$E14*$F14-$G14)) | K14: =IF(OR($C14="",$I14="No"),0,ROUND($J14*IFERROR(INDEX(Shows!$F$4:$F$23,MATCH($B14,Shows!$A$4:$A$23,0)),0),2)) | L14: =IF($C14="","",$E14*$H14) | M14: =IF($C14="","",$J14-$L14-$P14) | P14: =IF(OR($C14="",$N14<>"Card"),0,ROUND(($J14+$K14)*IFERROR(INDEX(Shows!$G$4:$G$23,MATCH($B14,Shows!$A$4:$A$23,0)),0)+IFERROR(INDEX(Shows!$H$4:$H$23,MATCH($B14,Shows!$A$4:$A$23,0)),0),2)) | Q14: =IF($C14="","",$J14+$K14-$P14)
D15: =IF($C15="","",IFERROR(INDEX(Inventory!$B$4:$B$253,MATCH($C15,Inventory!$A$4:$A$253,0))&" "&INDEX(Inventory!$C$4:$C$253,MATCH($C15,Inventory!$A$4:$A$253,0)),"SKU not in Inventory")) | H15: =IF($C15="","",IFERROR(INDEX(Inventory!$H$4:$H$253,MATCH($C15,Inventory!$A$4:$A$253,0)),0)) | J15: =IF($C15="","",MAX(0,$E15*$F15-$G15)) | K15: =IF(OR($C15="",$I15="No"),0,ROUND($J15*IFERROR(INDEX(Shows!$F$4:$F$23,MATCH($B15,Shows!$A$4:$A$23,0)),0),2)) | L15: =IF($C15="","",$E15*$H15) | M15: =IF($C15="","",$J15-$L15-$P15) | P15: =IF(OR($C15="",$N15<>"Card"),0,ROUND(($J15+$K15)*IFERROR(INDEX(Shows!$G$4:$G$23,MATCH($B15,Shows!$A$4:$A$23,0)),0)+IFERROR(INDEX(Shows!$H$4:$H$23,MATCH($B15,Shows!$A$4:$A$23,0)),0),2)) | Q15: =IF($C15="","",$J15+$K15-$P15)
... D503: =IF($C503="","",IFERROR(INDEX(Inventory!$B$4:$B$253,MATCH($C503,Inventory!$A$4:$A$253,0))&" "&INDEX(Inventory!$C$4:$C$253,MATCH($C503,Inventory!$A$4:$A$253,0)),"SKU not in Inventory")) | H503: =IF($C503="","",IFERROR(INDEX(Inventory!$H$4:$H$253,MATCH($C503,Inventory!$A$4:$A$253,0)),0)) | J503: =IF($C503="","",MAX(0,$E503*$F503-$G503)) | K503: =IF(OR($C503="",$I503="No"),0,ROUND($J503*IFERROR(INDEX(Shows!$F$4:$F$23,MATCH($B503,Shows!$A$4:$A$23,0)),0),2)) | L503: =IF($C503="","",$E503*$H503) | M503: =IF($C503="","",$J503-$L503-$P503) | P503: =IF(OR($C503="",$N503<>"Card"),0,ROUND(($J503+$K503)*IFERROR(INDEX(Shows!$G$4:$G$23,MATCH($B503,Shows!$A$4:$A$23,0)),0)+IFERROR(INDEX(Shows!$H$4:$H$23,MATCH($B503,Shows!$A$4:$A$23,0)),0),2)) | Q503: =IF($C503="","",$J503+$K503-$P503)

Sheet Shows
A1: Shows — the fixed costs of showing up
A2: Blue cells are yours to fill in. TOTAL SHOW COST is calculated. VERIFY every tax rate with the state before you sell — the seeded values are typical combined state+local rates for the venue city, not legal advice.
A3: Show | B3: City | C3: State | D3: Start | E3: End | F3: Sales tax rate | G3: Card fee % | H3: Card flat $ | I3: Table / booth | J3: Travel | K3: Lodging | L3: Meals | M3: Shipping | N3: Other | O3: TOTAL SHOW COST | P3: Opening cash float | Q3: Notes
A4: SF Pen Show | B4: San Francisco Bay Area | C4: CA | F4: 0.09375 | G4: 0.026 | H4: 0.1 | O4: =IFERROR(SUM(I4:N4),0)
A5: Orlando Pen Show | B5: Orlando | C5: FL | F5: 0.065 | G5: 0.026 | H5: 0.1 | O5: =IFERROR(SUM(I5:N5),0)
A6: Dallas Pen Show | B6: Dallas | C6: TX | F6: 0.0825 | G6: 0.026 | H6: 0.1 | O6: =IFERROR(SUM(I6:N6),0)
A7: Denver Pen Show | B7: Denver | C7: CO | F7: 0.0881 | G7: 0.026 | H7: 0.1 | O7: =IFERROR(SUM(I7:N7),0)
A8: Ohio Pen Show | B8: Columbus | C8: OH | F8: 0.075 | G8: 0.026 | H8: 0.1 | O8: =IFERROR(SUM(I8:N8),0)
O9: =IFERROR(SUM(I9:N9),0)
O10: =IFERROR(SUM(I10:N10),0)
O11: =IFERROR(SUM(I11:N11),0)
O12: =IFERROR(SUM(I12:N12),0)
O13: =IFERROR(SUM(I13:N13),0)
O14: =IFERROR(SUM(I14:N14),0)
O15: =IFERROR(SUM(I15:N15),0)
O16: =IFERROR(SUM(I16:N16),0)
O17: =IFERROR(SUM(I17:N17),0)
O18: =IFERROR(SUM(I18:N18),0)
O19: =IFERROR(SUM(I19:N19),0)
O20: =IFERROR(SUM(I20:N20),0)
... O23: =IFERROR(SUM(I23:N23),0)

Sheet Lists
A1: Validation lists
A2: Add your own values down each column; the dropdowns pick them up automatically.
A3: Category | B3: Nib | C3: Condition | D3: Payment | E3: Yes/No
A4: Pen | B4: EF | C4: New | D4: Cash | E4: Yes
A5: Vintage Pen | B5: F | C5: New old stock | D5: Zelle | E5: No
A6: Nib | B6: M | C6: Restored | D6: Venmo
A7: Ink | B7: B | C7: Used - excellent | D7: Card
A8: Paper | B8: BB | C8: Used - good | D8: Check
A9: Accessory | B9: Stub | C9: For parts | D9: Trade
A10: Service | B10: Italic | D10: Split
B11: Architect
B12: Music
B13: Flex
B14: Zoom
B15: Fude
B16: Needlepoint
B17: n/a
